[{"titulo":"Moore, Russel and Hilll","description":"grow robust functionalities"},
{"titulo":"Bayer-Pollich","description":"redefine ubiquitous channels"},
{"titulo":"Hermiston, Kling and Howe","description":"iterate proactive architectures"},
{"titulo":"Connelly, Homenick and Ratke","description":"harness cutting-edge users"},
{"titulo":"Rice-Marquardt","description":"synergize 24/365 schemas"},
{"titulo":"Rice, Ortiz and Ernser","description":"morph open-source convergence"},
{"titulo":"Simonis, Hilpert and Runolfsson","description":"enhance viral interfaces"},
{"titulo":"Rath, Bednar and Pfeffer","description":"integrate rich metrics"},
{"titulo":"Cormier Group","description":"engage scalable relationships"},
{"titulo":"Bins Inc","description":"envisioneer value-added platforms"}]